crawlpy/__init__.py
crawlpy/webscraper.py
crawlpy/youtubescraper.py
tests/__init__.py
tests/test_scraper.py
crawlpy-1.0.2.dist-info/METADATA
crawlpy-1.0.2.dist-info/WHEEL
crawlpy-1.0.2.dist-info/top_level.txt
crawlpy-1.0.2.dist-info/RECORD
