Metadata-Version: 2.1
Name: crawlpy
Version: 1.0.2
Summary: A Python package for web scraping and YouTube video scraping
Home-page: https://github.com/PraNavKumAr01/crawlpy
Author: Pranav Kumar
Author-email: pranavkumarnair@gmail.com
Classifier: Programming Language :: Python :: 3
Classifier: License :: OSI Approved :: MIT License
Classifier: Operating System :: OS Independent
Requires-Dist: requests
Requires-Dist: beautifulsoup4
Requires-Dist: pytube
Requires-Dist: deepgram-sdk
Requires-Dist: httpx
Requires-Dist: python-dotenv
